easy_sqlserver/__init__.py
easy_sqlserver/con.py
easy_sqlserver/easy_sqlserver.py
easy_sqlserver/filters/__init__.py
easy_sqlserver/filters/filters.py
easy_sqlserver-0.0.9.dist-info/METADATA
easy_sqlserver-0.0.9.dist-info/RECORD
easy_sqlserver-0.0.9.dist-info/WHEEL
easy_sqlserver-0.0.9.dist-info/top_level.txt
